[
  {
    "timestamp": "2025-07-26T09:40:34.891656",
    "persisted": true,
    "system": {
      "cpu_usage": 12.0,
      "cpu_user": 7.4,
      "cpu_breakdown": {
        "total": 12.0,
        "user": 7.4,
        "kernel": 5.2,
        "iowait": 0.0,
        "softirq": 0.0
      },
      "memory_system_total": 5700.15,
      "memory_system_available": 3293.69,
      "memory_usage_percent": 42.22,
      "memory_percent": 42.22,
      "memory_system_used": 2406.46,
      "battery_level": 100.0,
      "network_rx_total": 6059.97,
      "network_tx_total": 2810.34,
      "network": 0.0,
      "network_rx": 0.0,
      "network_tx": 0.0,
      "load_1min": 23.26,
      "load_5min": 23.56,
      "load_15min": 23.33
    },
    "apps": [
      {
        "app_package": "com.hihonor.calculator",
        "cpu_usage": 2.2,
        "memory_pss": 45.86,
        "memory_java": 8.57,
        "memory_native": 5.11,
        "frame_count": 85.0,
        "jank_frames": 23.0,
        "jank_percent": 27.06,
        "gpu_p50_ms": 3.0,
        "gpu_p90_ms": 4.0,
        "gpu_p95_ms": 5.0,
        "gpu_p99_ms": 7.0,
        "power_consumption": 3900.0,
        "wakelock_count": 1,
        "top_cpu_usage": 0.0,
        "top_memory_percent": 1.5,
        "top_memory_res_kb": 90112.0,
        "app_info": {
          "package_name": "com.hihonor.calculator",
          "app_name": "com.hihonor.calculator"
        },
        "package_name": "com.hihonor.calculator"
      }
    ],
    "metadata": {
      "backend": "legacy_adb"
    }
  },
  {
    "timestamp": "2025-07-26T09:40:41.143412",
    "persisted": true,
    "system": {
      "cpu_usage": 12.0,
      "cpu_user": 7.4,
      "cpu_breakdown": {
        "total": 12.0,
        "user": 7.4,
        "kernel": 5.2,
        "iowait": 0.0,
        "softirq": 0.0
      },
      "memory_system_total": 5700.15,
      "memory_system_available": 3335.48,
      "memory_usage_percent": 41.48,
      "memory_percent": 41.48,
      "memory_system_used": 2364.67,
      "battery_level": 100.0,
      "network_rx_total": 6059.97,
      "network_tx_total": 2810.34,
      "network_rx": 0,
      "network_tx": 0,
      "network": 0,
      "load_1min": 23.26,
      "load_5min": 23.56,
      "load_15min": 23.33
    },
    "apps": [
      {
        "app_package": "com.hihonor.calculator",
        "cpu_usage": 2.2,
        "memory_pss": 45.69,
        "memory_java": 8.41,
        "memory_native": 5.13,
        "frame_count": 85.0,
        "jank_frames": 23.0,
        "jank_percent": 27.06,
        "gpu_p50_ms": 3.0,
        "gpu_p90_ms": 4.0,
        "gpu_p95_ms": 5.0,
        "gpu_p99_ms": 7.0,
        "power_consumption": 3900.0,
        "wakelock_count": 1,
        "top_cpu_usage": 0.0,
        "top_memory_percent": 1.5,
        "top_memory_res_kb": 89088.0,
        "app_info": {
          "package_name": "com.hihonor.calculator",
          "app_name": "com.hihonor.calculator"
        },
        "package_name": "com.hihonor.calculator"
      }
    ],
    "metadata": {
      "backend": "legacy_adb"
    }
  },
  {
    "timestamp": "2025-07-26T09:40:47.416108",
    "persisted": true,
    "system": {
      "cpu_usage": 12.0,
      "cpu_user": 7.4,
      "cpu_breakdown": {
        "total": 12.0,
        "user": 7.4,
        "kernel": 5.2,
        "iowait": 0.0,
        "softirq": 0.0
      },
      "memory_system_total": 5700.15,
      "memory_system_available": 3333.82,
      "memory_usage_percent": 41.51,
      "memory_percent": 41.51,
      "memory_system_used": 2366.33,
      "battery_level": 100.0,
      "network_rx_total": 6059.97,
      "network_tx_total": 2810.34,
      "network_rx": 0,
      "network_tx": 0,
      "network": 0,
      "load_1min": 23.26,
      "load_5min": 23.56,
      "load_15min": 23.33
    },
    "apps": [
      {
        "app_package": "com.hihonor.calculator",
        "cpu_usage": 2.2,
        "memory_pss": 45.71,
        "memory_java": 8.43,
        "memory_native": 5.12,
        "frame_count": 85.0,
        "jank_frames": 23.0,
        "jank_percent": 27.06,
        "gpu_p50_ms": 3.0,
        "gpu_p90_ms": 4.0,
        "gpu_p95_ms": 5.0,
        "gpu_p99_ms": 7.0,
        "power_consumption": 3900.0,
        "wakelock_count": 1,
        "top_cpu_usage": 0.0,
        "top_memory_percent": 1.5,
        "top_memory_res_kb": 89088.0,
        "app_info": {
          "package_name": "com.hihonor.calculator",
          "app_name": "com.hihonor.calculator"
        },
        "package_name": "com.hihonor.calculator"
      }
    ],
    "metadata": {
      "backend": "legacy_adb"
    }
  },
  {
    "timestamp": "2025-07-26T09:40:54.082434",
    "persisted": true,
    "system": {
      "cpu_usage": 12.0,
      "cpu_user": 7.4,
      "cpu_breakdown": {
        "total": 12.0,
        "user": 7.4,
        "kernel": 5.2,
        "iowait": 0.0,
        "softirq": 0.0
      },
      "memory_system_total": 5700.15,
      "memory_system_available": 3256.52,
      "memory_usage_percent": 42.87,
      "memory_percent": 42.87,
      "memory_system_used": 2443.62,
      "battery_level": 100.0,
      "network_rx_total": 6059.97,
      "network_tx_total": 2810.34,
      "network_rx": 0,
      "network_tx": 0,
      "network": 0,
      "load_1min": 23.26,
      "load_5min": 23.56,
      "load_15min": 23.33
    },
    "apps": [
      {
        "app_package": "com.hihonor.calculator",
        "cpu_usage": 2.2,
        "memory_pss": 40.08,
        "memory_java": 8.49,
        "memory_native": 5.02,
        "frame_count": 86.0,
        "jank_frames": 23.0,
        "jank_percent": 26.74,
        "gpu_p50_ms": 3.0,
        "gpu_p90_ms": 4.0,
        "gpu_p95_ms": 5.0,
        "gpu_p99_ms": 7.0,
        "power_consumption": 3900.0,
        "wakelock_count": 1,
        "top_cpu_usage": 2.1,
        "top_memory_percent": 1.4,
        "top_memory_res_kb": 83968.0,
        "app_info": {
          "package_name": "com.hihonor.calculator",
          "app_name": "com.hihonor.calculator"
        },
        "package_name": "com.hihonor.calculator"
      }
    ],
    "metadata": {
      "backend": "legacy_adb"
    }
  },
  {
    "timestamp": "2025-07-26T09:41:04.331838",
    "persisted": true,
    "system": {
      "cpu_usage": 12.0,
      "cpu_user": 7.4,
      "cpu_breakdown": {
        "total": 12.0,
        "user": 7.4,
        "kernel": 5.2,
        "iowait": 0.0,
        "softirq": 0.0
      },
      "memory_system_total": 5700.15,
      "memory_system_available": 3279.29,
      "memory_usage_percent": 42.47,
      "memory_percent": 42.47,
      "memory_system_used": 2420.86,
      "battery_level": 100.0,
      "network_rx_total": 6059.97,
      "network_tx_total": 2810.34,
      "network_rx": 0,
      "network_tx": 0,
      "network": 0,
      "load_1min": 23.26,
      "load_5min": 23.56,
      "load_15min": 23.33
    },
    "apps": [
      {
        "app_package": "com.hihonor.calculator",
        "cpu_usage": 2.2,
        "memory_pss": 35.07,
        "memory_java": 0.08,
        "memory_native": 0.05,
        "frame_count": 86.0,
        "jank_frames": 23.0,
        "jank_percent": 26.74,
        "gpu_p50_ms": 3.0,
        "gpu_p90_ms": 4.0,
        "gpu_p95_ms": 5.0,
        "gpu_p99_ms": 7.0,
        "power_consumption": 3900.0,
        "wakelock_count": 1,
        "top_cpu_usage": 0.0,
        "top_memory_percent": 0.9,
        "top_memory_res_kb": 55296.0,
        "app_info": {
          "package_name": "com.hihonor.calculator",
          "app_name": "com.hihonor.calculator"
        },
        "package_name": "com.hihonor.calculator"
      }
    ],
    "metadata": {
      "backend": "legacy_adb"
    }
  },
  {
    "timestamp": "2025-07-26T09:41:10.790561",
    "persisted": true,
    "system": {
      "cpu_usage": 12.0,
      "cpu_user": 7.4,
      "cpu_breakdown": {
        "total": 12.0,
        "user": 7.4,
        "kernel": 5.2,
        "iowait": 0.0,
        "softirq": 0.0
      },
      "memory_system_total": 5700.15,
      "memory_system_available": 3336.34,
      "memory_usage_percent": 41.47,
      "memory_percent": 41.47,
      "memory_system_used": 2363.81,
      "battery_level": 100.0,
      "network_rx_total": 6081.69,
      "network_tx_total": 2823.49,
      "network_rx": 2.1,
      "network_tx": 1.27,
      "network": 3.37,
      "load_1min": 23.47,
      "load_5min": 23.58,
      "load_15min": 23.34
    },
    "apps": [
      {
        "app_package": "com.hihonor.calculator",
        "cpu_usage": 2.2,
        "memory_pss": 45.81,
        "memory_java": 8.53,
        "memory_native": 5.12,
        "frame_count": 89.0,
        "jank_frames": 24.0,
        "jank_percent": 26.97,
        "gpu_p50_ms": 3.0,
        "gpu_p90_ms": 4.0,
        "gpu_p95_ms": 5.0,
        "gpu_p99_ms": 7.0,
        "power_consumption": 3900.0,
        "wakelock_count": 1,
        "top_cpu_usage": 0.0,
        "top_memory_percent": 1.5,
        "top_memory_res_kb": 89088.0,
        "app_info": {
          "package_name": "com.hihonor.calculator",
          "app_name": "com.hihonor.calculator"
        },
        "package_name": "com.hihonor.calculator"
      }
    ],
    "metadata": {
      "backend": "legacy_adb"
    }
  },
  {
    "timestamp": "2025-07-26T09:41:17.002116",
    "persisted": true,
    "system": {
      "cpu_usage": 12.0,
      "cpu_user": 7.4,
      "cpu_breakdown": {
        "total": 12.0,
        "user": 7.4,
        "kernel": 5.2,
        "iowait": 0.0,
        "softirq": 0.0
      },
      "memory_system_total": 5700.15,
      "memory_system_available": 3332.95,
      "memory_usage_percent": 41.53,
      "memory_percent": 41.53,
      "memory_system_used": 2367.2,
      "battery_level": 100.0,
      "network_rx_total": 6081.69,
      "network_tx_total": 2823.49,
      "network_rx": 0,
      "network_tx": 0,
      "network": 0,
      "load_1min": 23.47,
      "load_5min": 23.58,
      "load_15min": 23.34
    },
    "apps": [
      {
        "app_package": "com.hihonor.calculator",
        "cpu_usage": 2.2,
        "memory_pss": 45.68,
        "memory_java": 8.41,
        "memory_native": 5.14,
        "frame_count": 89.0,
        "jank_frames": 24.0,
        "jank_percent": 26.97,
        "gpu_p50_ms": 3.0,
        "gpu_p90_ms": 4.0,
        "gpu_p95_ms": 5.0,
        "gpu_p99_ms": 7.0,
        "power_consumption": 3900.0,
        "wakelock_count": 1,
        "top_cpu_usage": 0.0,
        "top_memory_percent": 1.5,
        "top_memory_res_kb": 89088.0,
        "app_info": {
          "package_name": "com.hihonor.calculator",
          "app_name": "com.hihonor.calculator"
        },
        "package_name": "com.hihonor.calculator"
      }
    ],
    "metadata": {
      "backend": "legacy_adb"
    }
  },
  {
    "timestamp": "2025-07-26T09:41:23.556610",
    "persisted": true,
    "system": {
      "cpu_usage": 12.0,
      "cpu_user": 7.4,
      "cpu_breakdown": {
        "total": 12.0,
        "user": 7.4,
        "kernel": 5.2,
        "iowait": 0.0,
        "softirq": 0.0
      },
      "memory_system_total": 5700.15,
      "memory_system_available": 3259.13,
      "memory_usage_percent": 42.82,
      "memory_percent": 42.82,
      "memory_system_used": 2441.02,
      "battery_level": 100.0,
      "network_rx_total": 6081.69,
      "network_tx_total": 2823.49,
      "network_rx": 0,
      "network_tx": 0,
      "network": 0,
      "load_1min": 23.47,
      "load_5min": 23.58,
      "load_15min": 23.34
    },
    "apps": [
      {
        "app_package": "com.hihonor.calculator",
        "cpu_usage": 2.2,
        "memory_pss": 40.31,
        "memory_java": 8.47,
        "memory_native": 5.02,
        "frame_count": 90.0,
        "jank_frames": 24.0,
        "jank_percent": 26.67,
        "gpu_p50_ms": 3.0,
        "gpu_p90_ms": 4.0,
        "gpu_p95_ms": 5.0,
        "gpu_p99_ms": 12.0,
        "power_consumption": 3900.0,
        "wakelock_count": 1,
        "top_cpu_usage": 2.7,
        "top_memory_percent": 1.5,
        "top_memory_res_kb": 89088.0,
        "app_info": {
          "package_name": "com.hihonor.calculator",
          "app_name": "com.hihonor.calculator"
        },
        "package_name": "com.hihonor.calculator"
      }
    ],
    "metadata": {
      "backend": "legacy_adb"
    }
  },
  {
    "timestamp": "2025-07-26T09:41:34.671823",
    "persisted": true,
    "system": {
      "cpu_usage": 12.0,
      "cpu_user": 7.4,
      "cpu_breakdown": {
        "total": 12.0,
        "user": 7.4,
        "kernel": 5.2,
        "iowait": 0.0,
        "softirq": 0.0
      },
      "memory_system_total": 5700.15,
      "memory_system_available": 3284.34,
      "memory_usage_percent": 42.38,
      "memory_percent": 42.38,
      "memory_system_used": 2415.8,
      "battery_level": 100.0,
      "network_rx_total": 6081.69,
      "network_tx_total": 2823.49,
      "network_rx": 0,
      "network_tx": 0,
      "network": 0,
      "load_1min": 23.47,
      "load_5min": 23.58,
      "load_15min": 23.34
    },
    "apps": [
      {
        "app_package": "com.hihonor.calculator",
        "cpu_usage": 2.2,
        "memory_pss": 35.07,
        "memory_java": 0.08,
        "memory_native": 0.05,
        "frame_count": 90.0,
        "jank_frames": 24.0,
        "jank_percent": 26.67,
        "gpu_p50_ms": 3.0,
        "gpu_p90_ms": 4.0,
        "gpu_p95_ms": 5.0,
        "gpu_p99_ms": 12.0,
        "power_consumption": 3900.0,
        "wakelock_count": 1,
        "top_cpu_usage": 0.0,
        "top_memory_percent": 0.9,
        "top_memory_res_kb": 55296.0,
        "app_info": {
          "package_name": "com.hihonor.calculator",
          "app_name": "com.hihonor.calculator"
        },
        "package_name": "com.hihonor.calculator"
      }
    ],
    "metadata": {
      "backend": "legacy_adb"
    }
  },
  {
    "timestamp": "2025-07-26T09:41:41.151247",
    "persisted": true,
    "system": {
      "cpu_usage": 12.0,
      "cpu_user": 7.4,
      "cpu_breakdown": {
        "total": 12.0,
        "user": 7.4,
        "kernel": 5.2,
        "iowait": 0.0,
        "softirq": 0.0
      },
      "memory_system_total": 5700.15,
      "memory_system_available": 3325.52,
      "memory_usage_percent": 41.66,
      "memory_percent": 41.66,
      "memory_system_used": 2374.63,
      "battery_level": 100.0,
      "network_rx_total": 6093.57,
      "network_tx_total": 2830.09,
      "network_rx": 1.06,
      "network_tx": 0.59,
      "network": 1.65,
      "load_1min": 23.51,
      "load_5min": 23.59,
      "load_15min": 23.35
    },
    "apps": [
      {
        "app_package": "com.hihonor.calculator",
        "cpu_usage": 2.2,
        "memory_pss": 45.77,
        "memory_java": 8.5,
        "memory_native": 5.16,
        "frame_count": 93.0,
        "jank_frames": 25.0,
        "jank_percent": 26.88,
        "gpu_p50_ms": 3.0,
        "gpu_p90_ms": 4.0,
        "gpu_p95_ms": 5.0,
        "gpu_p99_ms": 12.0,
        "power_consumption": 3900.0,
        "wakelock_count": 1,
        "top_cpu_usage": 0.0,
        "top_memory_percent": 1.5,
        "top_memory_res_kb": 90112.0,
        "app_info": {
          "package_name": "com.hihonor.calculator",
          "app_name": "com.hihonor.calculator"
        },
        "package_name": "com.hihonor.calculator"
      }
    ],
    "metadata": {
      "backend": "legacy_adb"
    }
  },
  {
    "timestamp": "2025-07-26T09:41:47.382855",
    "persisted": true,
    "system": {
      "cpu_usage": 12.0,
      "cpu_user": 7.4,
      "cpu_breakdown": {
        "total": 12.0,
        "user": 7.4,
        "kernel": 5.2,
        "iowait": 0.0,
        "softirq": 0.0
      },
      "memory_system_total": 5700.15,
      "memory_system_available": 3323.26,
      "memory_usage_percent": 41.7,
      "memory_percent": 41.7,
      "memory_system_used": 2376.89,
      "battery_level": 100.0,
      "network_rx_total": 6093.57,
      "network_tx_total": 2830.09,
      "network_rx": 0,
      "network_tx": 0,
      "network": 0,
      "load_1min": 23.51,
      "load_5min": 23.59,
      "load_15min": 23.35
    },
    "apps": [
      {
        "app_package": "com.hihonor.calculator",
        "cpu_usage": 2.2,
        "memory_pss": 45.71,
        "memory_java": 8.44,
        "memory_native": 5.16,
        "frame_count": 93.0,
        "jank_frames": 25.0,
        "jank_percent": 26.88,
        "gpu_p50_ms": 3.0,
        "gpu_p90_ms": 4.0,
        "gpu_p95_ms": 5.0,
        "gpu_p99_ms": 12.0,
        "power_consumption": 3900.0,
        "wakelock_count": 1,
        "top_cpu_usage": 0.0,
        "top_memory_percent": 1.5,
        "top_memory_res_kb": 89088.0,
        "app_info": {
          "package_name": "com.hihonor.calculator",
          "app_name": "com.hihonor.calculator"
        },
        "package_name": "com.hihonor.calculator"
      }
    ],
    "metadata": {
      "backend": "legacy_adb"
    }
  },
  {
    "timestamp": "2025-07-26T09:41:53.781277",
    "persisted": true,
    "system": {
      "cpu_usage": 12.0,
      "cpu_user": 7.4,
      "cpu_breakdown": {
        "total": 12.0,
        "user": 7.4,
        "kernel": 5.2,
        "iowait": 0.0,
        "softirq": 0.0
      },
      "memory_system_total": 5700.15,
      "memory_system_available": 3253.23,
      "memory_usage_percent": 42.93,
      "memory_percent": 42.93,
      "memory_system_used": 2446.92,
      "battery_level": 100.0,
      "network_rx_total": 6093.57,
      "network_tx_total": 2830.09,
      "network_rx": 0,
      "network_tx": 0,
      "network": 0,
      "load_1min": 23.51,
      "load_5min": 23.59,
      "load_15min": 23.35
    },
    "apps": [
      {
        "app_package": "com.hihonor.calculator",
        "cpu_usage": 2.2,
        "memory_pss": 40.84,
        "memory_java": 8.47,
        "memory_native": 5.08,
        "frame_count": 94.0,
        "jank_frames": 25.0,
        "jank_percent": 26.6,
        "gpu_p50_ms": 3.0,
        "gpu_p90_ms": 4.0,
        "gpu_p95_ms": 5.0,
        "gpu_p99_ms": 12.0,
        "power_consumption": 3900.0,
        "wakelock_count": 1,
        "top_cpu_usage": 0.0,
        "top_memory_percent": 1.5,
        "top_memory_res_kb": 89088.0,
        "app_info": {
          "package_name": "com.hihonor.calculator",
          "app_name": "com.hihonor.calculator"
        },
        "package_name": "com.hihonor.calculator"
      }
    ],
    "metadata": {
      "backend": "legacy_adb"
    }
  },
  {
    "timestamp": "2025-07-26T09:42:05.034336",
    "persisted": true,
    "system": {
      "cpu_usage": 12.0,
      "cpu_user": 7.4,
      "cpu_breakdown": {
        "total": 12.0,
        "user": 7.4,
        "kernel": 5.2,
        "iowait": 0.0,
        "softirq": 0.0
      },
      "memory_system_total": 5700.15,
      "memory_system_available": 3279.81,
      "memory_usage_percent": 42.46,
      "memory_percent": 42.46,
      "memory_system_used": 2420.34,
      "battery_level": 100.0,
      "network_rx_total": 6093.57,
      "network_tx_total": 2830.09,
      "network_rx": 0,
      "network_tx": 0,
      "network": 0,
      "load_1min": 23.51,
      "load_5min": 23.59,
      "load_15min": 23.35
    },
    "apps": [
      {
        "app_package": "com.hihonor.calculator",
        "cpu_usage": 2.2,
        "memory_pss": 35.13,
        "memory_java": 0.08,
        "memory_native": 0.05,
        "frame_count": 94.0,
        "jank_frames": 25.0,
        "jank_percent": 26.6,
        "gpu_p50_ms": 3.0,
        "gpu_p90_ms": 4.0,
        "gpu_p95_ms": 5.0,
        "gpu_p99_ms": 12.0,
        "power_consumption": 3900.0,
        "wakelock_count": 1,
        "top_cpu_usage": 0.0,
        "top_memory_percent": 0.9,
        "top_memory_res_kb": 55296.0,
        "app_info": {
          "package_name": "com.hihonor.calculator",
          "app_name": "com.hihonor.calculator"
        },
        "package_name": "com.hihonor.calculator"
      }
    ],
    "metadata": {
      "backend": "legacy_adb"
    }
  },
  {
    "timestamp": "2025-07-26T09:42:11.566269",
    "persisted": true,
    "system": {
      "cpu_usage": 12.0,
      "cpu_user": 7.4,
      "cpu_breakdown": {
        "total": 12.0,
        "user": 7.4,
        "kernel": 5.2,
        "iowait": 0.0,
        "softirq": 0.0
      },
      "memory_system_total": 5700.15,
      "memory_system_available": 3326.54,
      "memory_usage_percent": 41.64,
      "memory_percent": 41.64,
      "memory_system_used": 2373.61,
      "battery_level": 100.0,
      "network_rx_total": 6105.38,
      "network_tx_total": 2836.59,
      "network_rx": 1.04,
      "network_tx": 0.57,
      "network": 1.61,
      "load_1min": 23.39,
      "load_5min": 23.56,
      "load_15min": 23.35
    },
    "apps": [
      {
        "app_package": "com.hihonor.calculator",
        "cpu_usage": 2.2,
        "memory_pss": 46.04,
        "memory_java": 8.55,
        "memory_native": 5.15,
        "frame_count": 97.0,
        "jank_frames": 26.0,
        "jank_percent": 26.8,
        "gpu_p50_ms": 3.0,
        "gpu_p90_ms": 4.0,
        "gpu_p95_ms": 5.0,
        "gpu_p99_ms": 12.0,
        "power_consumption": 3900.0,
        "wakelock_count": 1,
        "top_cpu_usage": 0.0,
        "top_memory_percent": 1.5,
        "top_memory_res_kb": 89088.0,
        "app_info": {
          "package_name": "com.hihonor.calculator",
          "app_name": "com.hihonor.calculator"
        },
        "package_name": "com.hihonor.calculator"
      }
    ],
    "metadata": {
      "backend": "legacy_adb"
    }
  },
  {
    "timestamp": "2025-07-26T09:42:17.910584",
    "persisted": true,
    "system": {
      "cpu_usage": 12.0,
      "cpu_user": 7.4,
      "cpu_breakdown": {
        "total": 12.0,
        "user": 7.4,
        "kernel": 5.0,
        "iowait": 0.0,
        "softirq": 0.0
      },
      "memory_system_total": 5700.15,
      "memory_system_available": 3321.93,
      "memory_usage_percent": 41.72,
      "memory_percent": 41.72,
      "memory_system_used": 2378.22,
      "battery_level": 100.0,
      "network_rx_total": 6105.38,
      "network_tx_total": 2836.59,
      "network_rx": 0,
      "network_tx": 0,
      "network": 0,
      "load_1min": 23.39,
      "load_5min": 23.56,
      "load_15min": 23.35
    },
    "apps": [
      {
        "app_package": "com.hihonor.calculator",
        "cpu_usage": 2.4,
        "memory_pss": 45.91,
        "memory_java": 8.41,
        "memory_native": 5.16,
        "frame_count": 97.0,
        "jank_frames": 26.0,
        "jank_percent": 26.8,
        "gpu_p50_ms": 3.0,
        "gpu_p90_ms": 4.0,
        "gpu_p95_ms": 5.0,
        "gpu_p99_ms": 12.0,
        "power_consumption": 3900.0,
        "wakelock_count": 1,
        "top_cpu_usage": 0.0,
        "top_memory_percent": 1.5,
        "top_memory_res_kb": 89088.0,
        "app_info": {
          "package_name": "com.hihonor.calculator",
          "app_name": "com.hihonor.calculator"
        },
        "package_name": "com.hihonor.calculator"
      }
    ],
    "metadata": {
      "backend": "legacy_adb"
    }
  },
  {
    "timestamp": "2025-07-26T09:42:24.414060",
    "persisted": true,
    "system": {
      "cpu_usage": 12.0,
      "cpu_user": 7.5,
      "cpu_breakdown": {
        "total": 12.0,
        "user": 7.5,
        "kernel": 4.5,
        "softirq": 0.0
      },
      "memory_system_total": 5700.15,
      "memory_system_available": 3268.09,
      "memory_usage_percent": 42.67,
      "memory_percent": 42.67,
      "memory_system_used": 2432.06,
      "battery_level": 100.0,
      "network_rx_total": 6105.38,
      "network_tx_total": 2836.59,
      "network_rx": 0,
      "network_tx": 0,
      "network": 0,
      "load_1min": 23.39,
      "load_5min": 23.56,
      "load_15min": 23.35
    },
    "apps": [
      {
        "app_package": "com.hihonor.calculator",
        "cpu_usage": 2.4,
        "memory_pss": 40.02,
        "memory_java": 8.46,
        "memory_native": 5.06,
        "frame_count": 98.0,
        "jank_frames": 26.0,
        "jank_percent": 26.53,
        "gpu_p50_ms": 3.0,
        "gpu_p90_ms": 4.0,
        "gpu_p95_ms": 5.0,
        "gpu_p99_ms": 12.0,
        "power_consumption": 3900.0,
        "wakelock_count": 1,
        "top_cpu_usage": 0.0,
        "top_memory_percent": 1.5,
        "top_memory_res_kb": 89088.0,
        "app_info": {
          "package_name": "com.hihonor.calculator",
          "app_name": "com.hihonor.calculator"
        },
        "package_name": "com.hihonor.calculator"
      }
    ],
    "metadata": {
      "backend": "legacy_adb"
    }
  },
  {
    "timestamp": "2025-07-26T09:42:35.412946",
    "persisted": true,
    "system": {
      "cpu_usage": 15.0,
      "cpu_user": 9.5,
      "cpu_breakdown": {
        "total": 15.0,
        "user": 9.5,
        "kernel": 6.3,
        "iowait": 0.0
      },
      "memory_system_total": 5700.15,
      "memory_system_available": 3275.39,
      "memory_usage_percent": 42.54,
      "memory_percent": 42.54,
      "memory_system_used": 2424.76,
      "battery_level": 100.0,
      "network_rx_total": 6105.38,
      "network_tx_total": 2836.59,
      "network_rx": 0,
      "network_tx": 0,
      "network": 0,
      "load_1min": 23.39,
      "load_5min": 23.56,
      "load_15min": 23.35
    },
    "apps": [
      {
        "app_package": "com.hihonor.calculator",
        "cpu_usage": 5.6,
        "memory_pss": 35.03,
        "memory_java": 0.08,
        "memory_native": 0.05,
        "frame_count": 98.0,
        "jank_frames": 26.0,
        "jank_percent": 26.53,
        "gpu_p50_ms": 3.0,
        "gpu_p90_ms": 4.0,
        "gpu_p95_ms": 5.0,
        "gpu_p99_ms": 12.0,
        "power_consumption": 3900.0,
        "wakelock_count": 1,
        "top_cpu_usage": 0.0,
        "top_memory_percent": 0.9,
        "top_memory_res_kb": 55296.0,
        "app_info": {
          "package_name": "com.hihonor.calculator",
          "app_name": "com.hihonor.calculator"
        },
        "package_name": "com.hihonor.calculator"
      }
    ],
    "metadata": {
      "backend": "legacy_adb"
    }
  },
  {
    "timestamp": "2025-07-26T09:42:41.830188",
    "persisted": true,
    "system": {
      "cpu_usage": 10.0,
      "cpu_user": 6.3,
      "cpu_breakdown": {
        "total": 10.0,
        "user": 6.3,
        "kernel": 3.9,
        "iowait": 0.0,
        "softirq": 0.0
      },
      "memory_system_total": 5700.15,
      "memory_system_available": 3316.82,
      "memory_usage_percent": 41.81,
      "memory_percent": 41.81,
      "memory_system_used": 2383.33,
      "battery_level": 100.0,
      "network_rx_total": 6116.98,
      "network_tx_total": 2843.23,
      "network_rx": 1.04,
      "network_tx": 0.6,
      "network": 1.64,
      "load_1min": 23.19,
      "load_5min": 23.5,
      "load_15min": 23.34
    },
    "apps": [
      {
        "app_package": "com.hihonor.calculator",
        "cpu_usage": 1.5,
        "memory_pss": 45.98,
        "memory_java": 8.52,
        "memory_native": 5.12,
        "frame_count": 101.0,
        "jank_frames": 27.0,
        "jank_percent": 26.73,
        "gpu_p50_ms": 3.0,
        "gpu_p90_ms": 4.0,
        "gpu_p95_ms": 5.0,
        "gpu_p99_ms": 7.0,
        "power_consumption": 3900.0,
        "wakelock_count": 1,
        "top_cpu_usage": 2.8,
        "top_memory_percent": 1.5,
        "top_memory_res_kb": 90112.0,
        "app_info": {
          "package_name": "com.hihonor.calculator",
          "app_name": "com.hihonor.calculator"
        },
        "package_name": "com.hihonor.calculator"
      }
    ],
    "metadata": {
      "backend": "legacy_adb"
    }
  },
  {
    "timestamp": "2025-07-26T09:42:48.064766",
    "persisted": true,
    "system": {
      "cpu_usage": 10.0,
      "cpu_user": 6.3,
      "cpu_breakdown": {
        "total": 10.0,
        "user": 6.3,
        "kernel": 3.9,
        "iowait": 0.0,
        "softirq": 0.0
      },
      "memory_system_total": 5700.15,
      "memory_system_available": 3314.3,
      "memory_usage_percent": 41.86,
      "memory_percent": 41.86,
      "memory_system_used": 2385.85,
      "battery_level": 100.0,
      "network_rx_total": 6116.98,
      "network_tx_total": 2843.23,
      "network_rx": 0,
      "network_tx": 0,
      "network": 0,
      "load_1min": 23.19,
      "load_5min": 23.5,
      "load_15min": 23.34
    },
    "apps": [
      {
        "app_package": "com.hihonor.calculator",
        "cpu_usage": 1.5,
        "memory_pss": 45.88,
        "memory_java": 8.41,
        "memory_native": 5.13,
        "frame_count": 101.0,
        "jank_frames": 27.0,
        "jank_percent": 26.73,
        "gpu_p50_ms": 3.0,
        "gpu_p90_ms": 4.0,
        "gpu_p95_ms": 5.0,
        "gpu_p99_ms": 7.0,
        "power_consumption": 3900.0,
        "wakelock_count": 1,
        "top_cpu_usage": 0.0,
        "top_memory_percent": 1.5,
        "top_memory_res_kb": 89088.0,
        "app_info": {
          "package_name": "com.hihonor.calculator",
          "app_name": "com.hihonor.calculator"
        },
        "package_name": "com.hihonor.calculator"
      }
    ],
    "metadata": {
      "backend": "legacy_adb"
    }
  },
  {
    "timestamp": "2025-07-26T09:42:54.630308",
    "persisted": true,
    "system": {
      "cpu_usage": 11.0,
      "cpu_user": 6.5,
      "cpu_breakdown": {
        "total": 11.0,
        "user": 6.5,
        "kernel": 5.2,
        "iowait": 0.0,
        "softirq": 0.0
      },
      "memory_system_total": 5700.15,
      "memory_system_available": 3250.94,
      "memory_usage_percent": 42.97,
      "memory_percent": 42.97,
      "memory_system_used": 2449.21,
      "battery_level": 100.0,
      "network_rx_total": 6116.98,
      "network_tx_total": 2843.23,
      "network_rx": 0,
      "network_tx": 0,
      "network": 0,
      "load_1min": 23.19,
      "load_5min": 23.5,
      "load_15min": 23.34
    },
    "apps": [
      {
        "app_package": "com.hihonor.calculator",
        "cpu_usage": 2.3,
        "memory_pss": 40.29,
        "memory_java": 8.46,
        "memory_native": 5.06,
        "frame_count": 102.0,
        "jank_frames": 27.0,
        "jank_percent": 26.47,
        "gpu_p50_ms": 3.0,
        "gpu_p90_ms": 4.0,
        "gpu_p95_ms": 5.0,
        "gpu_p99_ms": 7.0,
        "power_consumption": 3900.0,
        "wakelock_count": 1,
        "top_cpu_usage": 3.0,
        "top_memory_percent": 1.5,
        "top_memory_res_kb": 89088.0,
        "app_info": {
          "package_name": "com.hihonor.calculator",
          "app_name": "com.hihonor.calculator"
        },
        "package_name": "com.hihonor.calculator"
      }
    ],
    "metadata": {
      "backend": "legacy_adb"
    }
  },
  {
    "timestamp": "2025-07-26T09:43:05.736929",
    "persisted": true,
    "system": {
      "cpu_usage": 17.0,
      "cpu_user": 10.0,
      "cpu_breakdown": {
        "total": 17.0,
        "user": 10.0,
        "kernel": 6.5,
        "iowait": 0.0,
        "softirq": 0.0
      },
      "memory_system_total": 5700.15,
      "memory_system_available": 3265.71,
      "memory_usage_percent": 42.71,
      "memory_percent": 42.71,
      "memory_system_used": 2434.43,
      "battery_level": 100.0,
      "network_rx_total": 6116.98,
      "network_tx_total": 2843.23,
      "network_rx": 0,
      "network_tx": 0,
      "network": 0,
      "load_1min": 23.19,
      "load_5min": 23.5,
      "load_15min": 23.34
    },
    "apps": [
      {
        "app_package": "com.hihonor.calculator",
        "cpu_usage": 5.2,
        "memory_pss": 35.17,
        "memory_java": 0.08,
        "memory_native": 0.05,
        "frame_count": 102.0,
        "jank_frames": 27.0,
        "jank_percent": 26.47,
        "gpu_p50_ms": 3.0,
        "gpu_p90_ms": 4.0,
        "gpu_p95_ms": 5.0,
        "gpu_p99_ms": 7.0,
        "power_consumption": 3900.0,
        "wakelock_count": 1,
        "top_cpu_usage": 0.0,
        "top_memory_percent": 0.9,
        "top_memory_res_kb": 55296.0,
        "app_info": {
          "package_name": "com.hihonor.calculator",
          "app_name": "com.hihonor.calculator"
        },
        "package_name": "com.hihonor.calculator"
      }
    ],
    "metadata": {
      "backend": "legacy_adb"
    }
  },
  {
    "timestamp": "2025-07-26T09:43:12.307235",
    "persisted": true,
    "system": {
      "cpu_usage": 11.0,
      "cpu_user": 6.8,
      "cpu_breakdown": {
        "total": 11.0,
        "user": 6.8,
        "kernel": 4.5,
        "iowait": 0.0,
        "softirq": 0.0
      },
      "memory_system_total": 5700.15,
      "memory_system_available": 3313.15,
      "memory_usage_percent": 41.88,
      "memory_percent": 41.88,
      "memory_system_used": 2387.0,
      "battery_level": 100.0,
      "network_rx_total": 6132.21,
      "network_tx_total": 2852.95,
      "network_rx": 1.36,
      "network_tx": 0.87,
      "network": 2.23,
      "load_1min": 23.88,
      "load_5min": 23.64,
      "load_15min": 23.39
    },
    "apps": [
      {
        "app_package": "com.hihonor.calculator",
        "cpu_usage": 0.8,
        "memory_pss": 46.0,
        "memory_java": 8.53,
        "memory_native": 5.17,
        "frame_count": 105.0,
        "jank_frames": 28.0,
        "jank_percent": 26.67,
        "gpu_p50_ms": 3.0,
        "gpu_p90_ms": 4.0,
        "gpu_p95_ms": 5.0,
        "gpu_p99_ms": 7.0,
        "power_consumption": 3900.0,
        "wakelock_count": 1,
        "top_cpu_usage": 0.0,
        "top_memory_percent": 1.5,
        "top_memory_res_kb": 90112.0,
        "app_info": {
          "package_name": "com.hihonor.calculator",
          "app_name": "com.hihonor.calculator"
        },
        "package_name": "com.hihonor.calculator"
      }
    ],
    "metadata": {
      "backend": "legacy_adb"
    }
  },
  {
    "timestamp": "2025-07-26T09:43:18.662088",
    "persisted": true,
    "system": {
      "cpu_usage": 11.0,
      "cpu_user": 7.0,
      "cpu_breakdown": {
        "total": 11.0,
        "user": 7.0,
        "kernel": 4.9,
        "softirq": 0.0
      },
      "memory_system_total": 5700.15,
      "memory_system_available": 3309.02,
      "memory_usage_percent": 41.95,
      "memory_percent": 41.95,
      "memory_system_used": 2391.13,
      "battery_level": 100.0,
      "network_rx_total": 6132.21,
      "network_tx_total": 2852.95,
      "network_rx": 0,
      "network_tx": 0,
      "network": 0,
      "load_1min": 23.88,
      "load_5min": 23.64,
      "load_15min": 23.39
    },
    "apps": [
      {
        "app_package": "com.hihonor.calculator",
        "cpu_usage": 3.3,
        "memory_pss": 45.91,
        "memory_java": 8.44,
        "memory_native": 5.18,
        "frame_count": 105.0,
        "jank_frames": 28.0,
        "jank_percent": 26.67,
        "gpu_p50_ms": 3.0,
        "gpu_p90_ms": 4.0,
        "gpu_p95_ms": 5.0,
        "gpu_p99_ms": 7.0,
        "power_consumption": 3900.0,
        "wakelock_count": 1,
        "top_cpu_usage": 0.0,
        "top_memory_percent": 1.5,
        "top_memory_res_kb": 89088.0,
        "app_info": {
          "package_name": "com.hihonor.calculator",
          "app_name": "com.hihonor.calculator"
        },
        "package_name": "com.hihonor.calculator"
      }
    ],
    "metadata": {
      "backend": "legacy_adb"
    }
  },
  {
    "timestamp": "2025-07-26T09:43:25.146117",
    "persisted": true,
    "system": {
      "cpu_usage": 10.0,
      "cpu_user": 6.5,
      "cpu_breakdown": {
        "total": 10.0,
        "user": 6.5,
        "kernel": 4.0,
        "iowait": 0.0
      },
      "memory_system_total": 5700.15,
      "memory_system_available": 3247.97,
      "memory_usage_percent": 43.02,
      "memory_percent": 43.02,
      "memory_system_used": 2452.18,
      "battery_level": 100.0,
      "network_rx_total": 6132.21,
      "network_tx_total": 2852.95,
      "network_rx": 0,
      "network_tx": 0,
      "network": 0,
      "load_1min": 23.88,
      "load_5min": 23.64,
      "load_15min": 23.39
    },
    "apps": [
      {
        "app_package": "com.hihonor.calculator",
        "cpu_usage": 2.4,
        "memory_pss": 40.06,
        "memory_java": 8.49,
        "memory_native": 5.1,
        "frame_count": 106.0,
        "jank_frames": 28.0,
        "jank_percent": 26.42,
        "gpu_p50_ms": 3.0,
        "gpu_p90_ms": 4.0,
        "gpu_p95_ms": 5.0,
        "gpu_p99_ms": 7.0,
        "power_consumption": 3900.0,
        "wakelock_count": 1,
        "top_cpu_usage": 2.5,
        "top_memory_percent": 1.5,
        "top_memory_res_kb": 89088.0,
        "app_info": {
          "package_name": "com.hihonor.calculator",
          "app_name": "com.hihonor.calculator"
        },
        "package_name": "com.hihonor.calculator"
      }
    ],
    "metadata": {
      "backend": "legacy_adb"
    }
  },
  {
    "timestamp": "2025-07-26T09:43:36.145338",
    "persisted": true,
    "system": {
      "cpu_usage": 20.0,
      "cpu_user": 12.0,
      "cpu_breakdown": {
        "total": 20.0,
        "user": 12.0,
        "kernel": 8.1,
        "iowait": 0.0,
        "softirq": 0.0
      },
      "memory_system_total": 5700.15,
      "memory_system_available": 3263.31,
      "memory_usage_percent": 42.75,
      "memory_percent": 42.75,
      "memory_system_used": 2436.84,
      "battery_level": 100.0,
      "network_rx_total": 6132.21,
      "network_tx_total": 2852.95,
      "network_rx": 0,
      "network_tx": 0,
      "network": 0,
      "load_1min": 23.88,
      "load_5min": 23.64,
      "load_15min": 23.39
    },
    "apps": [
      {
        "app_package": "com.hihonor.calculator",
        "cpu_usage": 5.7,
        "memory_pss": 35.19,
        "memory_java": 0.08,
        "memory_native": 0.05,
        "frame_count": 106.0,
        "jank_frames": 28.0,
        "jank_percent": 26.42,
        "gpu_p50_ms": 3.0,
        "gpu_p90_ms": 4.0,
        "gpu_p95_ms": 5.0,
        "gpu_p99_ms": 7.0,
        "power_consumption": 3900.0,
        "wakelock_count": 1,
        "top_cpu_usage": 0.0,
        "top_memory_percent": 0.9,
        "top_memory_res_kb": 55296.0,
        "app_info": {
          "package_name": "com.hihonor.calculator",
          "app_name": "com.hihonor.calculator"
        },
        "package_name": "com.hihonor.calculator"
      }
    ],
    "metadata": {
      "backend": "legacy_adb"
    }
  },
  {
    "timestamp": "2025-07-26T09:43:42.616325",
    "persisted": true,
    "system": {
      "cpu_usage": 20.0,
      "cpu_user": 12.0,
      "cpu_breakdown": {
        "total": 20.0,
        "user": 12.0,
        "kernel": 8.1,
        "iowait": 0.0,
        "softirq": 0.0
      },
      "memory_system_total": 5700.15,
      "memory_system_available": 3302.69,
      "memory_usage_percent": 42.06,
      "memory_percent": 42.06,
      "memory_system_used": 2397.46,
      "battery_level": 100.0,
      "network_rx_total": 6144.04,
      "network_tx_total": 2861.55,
      "network_rx": 1.06,
      "network_tx": 0.77,
      "network": 1.84,
      "load_1min": 23.74,
      "load_5min": 23.62,
      "load_15min": 23.4
    },
    "apps": [
      {
        "app_package": "com.hihonor.calculator",
        "cpu_usage": 5.7,
        "memory_pss": 46.03,
        "memory_java": 8.55,
        "memory_native": 5.15,
        "frame_count": 109.0,
        "jank_frames": 29.0,
        "jank_percent": 26.61,
        "gpu_p50_ms": 3.0,
        "gpu_p90_ms": 4.0,
        "gpu_p95_ms": 5.0,
        "gpu_p99_ms": 7.0,
        "power_consumption": 3900.0,
        "wakelock_count": 1,
        "top_cpu_usage": 0.0,
        "top_memory_percent": 1.5,
        "top_memory_res_kb": 89088.0,
        "app_info": {
          "package_name": "com.hihonor.calculator",
          "app_name": "com.hihonor.calculator"
        },
        "package_name": "com.hihonor.calculator"
      }
    ],
    "metadata": {
      "backend": "legacy_adb"
    }
  },
  {
    "timestamp": "2025-07-26T09:43:48.871805",
    "persisted": true,
    "system": {
      "cpu_usage": 20.0,
      "cpu_user": 12.0,
      "cpu_breakdown": {
        "total": 20.0,
        "user": 12.0,
        "kernel": 8.1,
        "iowait": 0.0,
        "softirq": 0.0
      },
      "memory_system_total": 5700.15,
      "memory_system_available": 3299.7,
      "memory_usage_percent": 42.11,
      "memory_percent": 42.11,
      "memory_system_used": 2400.45,
      "battery_level": 100.0,
      "network_rx_total": 6144.04,
      "network_tx_total": 2861.55,
      "network_rx": 0,
      "network_tx": 0,
      "network": 0,
      "load_1min": 23.74,
      "load_5min": 23.62,
      "load_15min": 23.4
    },
    "apps": [
      {
        "app_package": "com.hihonor.calculator",
        "cpu_usage": 5.7,
        "memory_pss": 45.89,
        "memory_java": 8.41,
        "memory_native": 5.15,
        "frame_count": 109.0,
        "jank_frames": 29.0,
        "jank_percent": 26.61,
        "gpu_p50_ms": 3.0,
        "gpu_p90_ms": 4.0,
        "gpu_p95_ms": 5.0,
        "gpu_p99_ms": 7.0,
        "power_consumption": 3900.0,
        "wakelock_count": 1,
        "top_cpu_usage": 0.0,
        "top_memory_percent": 1.5,
        "top_memory_res_kb": 89088.0,
        "app_info": {
          "package_name": "com.hihonor.calculator",
          "app_name": "com.hihonor.calculator"
        },
        "package_name": "com.hihonor.calculator"
      }
    ],
    "metadata": {
      "backend": "legacy_adb"
    }
  },
  {
    "timestamp": "2025-07-26T09:43:55.316819",
    "persisted": true,
    "system": {
      "cpu_usage": 20.0,
      "cpu_user": 12.0,
      "cpu_breakdown": {
        "total": 20.0,
        "user": 12.0,
        "kernel": 8.1,
        "iowait": 0.0,
        "softirq": 0.0
      },
      "memory_system_total": 5700.15,
      "memory_system_available": 3252.91,
      "memory_usage_percent": 42.93,
      "memory_percent": 42.93,
      "memory_system_used": 2447.24,
      "battery_level": 100.0,
      "network_rx_total": 6144.04,
      "network_tx_total": 2861.55,
      "network_rx": 0,
      "network_tx": 0,
      "network": 0,
      "load_1min": 23.74,
      "load_5min": 23.62,
      "load_15min": 23.4
    },
    "apps": [
      {
        "app_package": "com.hihonor.calculator",
        "cpu_usage": 5.7,
        "memory_pss": 40.76,
        "memory_java": 8.46,
        "memory_native": 5.06,
        "frame_count": 110.0,
        "jank_frames": 30.0,
        "jank_percent": 27.27,
        "gpu_p50_ms": 3.0,
        "gpu_p90_ms": 4.0,
        "gpu_p95_ms": 5.0,
        "gpu_p99_ms": 11.0,
        "power_consumption": 3900.0,
        "wakelock_count": 1,
        "top_cpu_usage": 3.0,
        "top_memory_percent": 1.5,
        "top_memory_res_kb": 89088.0,
        "app_info": {
          "package_name": "com.hihonor.calculator",
          "app_name": "com.hihonor.calculator"
        },
        "package_name": "com.hihonor.calculator"
      }
    ],
    "metadata": {
      "backend": "legacy_adb"
    }
  },
  {
    "timestamp": "2025-07-26T09:44:06.499009",
    "persisted": true,
    "system": {
      "cpu_usage": 20.0,
      "cpu_user": 12.0,
      "cpu_breakdown": {
        "total": 20.0,
        "user": 12.0,
        "kernel": 8.1,
        "iowait": 0.0,
        "softirq": 0.0
      },
      "memory_system_total": 5700.15,
      "memory_system_available": 3262.53,
      "memory_usage_percent": 42.76,
      "memory_percent": 42.76,
      "memory_system_used": 2437.62,
      "battery_level": 100.0,
      "network_rx_total": 6144.04,
      "network_tx_total": 2861.55,
      "network_rx": 0,
      "network_tx": 0,
      "network": 0,
      "load_1min": 23.74,
      "load_5min": 23.62,
      "load_15min": 23.4
    },
    "apps": [
      {
        "app_package": "com.hihonor.calculator",
        "cpu_usage": 5.7,
        "memory_pss": 35.41,
        "memory_java": 0.08,
        "memory_native": 0.05,
        "frame_count": 110.0,
        "jank_frames": 30.0,
        "jank_percent": 27.27,
        "gpu_p50_ms": 3.0,
        "gpu_p90_ms": 4.0,
        "gpu_p95_ms": 5.0,
        "gpu_p99_ms": 11.0,
        "power_consumption": 3900.0,
        "wakelock_count": 1,
        "top_cpu_usage": 0.0,
        "top_memory_percent": 0.9,
        "top_memory_res_kb": 55296.0,
        "app_info": {
          "package_name": "com.hihonor.calculator",
          "app_name": "com.hihonor.calculator"
        },
        "package_name": "com.hihonor.calculator"
      }
    ],
    "metadata": {
      "backend": "legacy_adb"
    }
  },
  {
    "timestamp": "2025-07-26T09:44:13.048112",
    "persisted": true,
    "system": {
      "cpu_usage": 20.0,
      "cpu_user": 12.0,
      "cpu_breakdown": {
        "total": 20.0,
        "user": 12.0,
        "kernel": 8.1,
        "iowait": 0.0,
        "softirq": 0.0
      },
      "memory_system_total": 5700.15,
      "memory_system_available": 3303.39,
      "memory_usage_percent": 42.05,
      "memory_percent": 42.05,
      "memory_system_used": 2396.76,
      "battery_level": 100.0,
      "network_rx_total": 6162.51,
      "network_tx_total": 2870.27,
      "network_rx": 1.64,
      "network_tx": 0.78,
      "network": 2.42,
      "load_1min": 23.68,
      "load_5min": 23.61,
      "load_15min": 23.4
    },
    "apps": [
      {
        "app_package": "com.hihonor.calculator",
        "cpu_usage": 5.7,
        "memory_pss": 46.06,
        "memory_java": 8.52,
        "memory_native": 5.14,
        "frame_count": 113.0,
        "jank_frames": 31.0,
        "jank_percent": 27.43,
        "gpu_p50_ms": 3.0,
        "gpu_p90_ms": 4.0,
        "gpu_p95_ms": 5.0,
        "gpu_p99_ms": 11.0,
        "power_consumption": 3900.0,
        "wakelock_count": 1,
        "top_cpu_usage": 0.0,
        "top_memory_percent": 1.5,
        "top_memory_res_kb": 90112.0,
        "app_info": {
          "package_name": "com.hihonor.calculator",
          "app_name": "com.hihonor.calculator"
        },
        "package_name": "com.hihonor.calculator"
      }
    ],
    "metadata": {
      "backend": "legacy_adb"
    }
  },
  {
    "timestamp": "2025-07-26T09:44:19.283977",
    "persisted": true,
    "system": {
      "cpu_usage": 20.0,
      "cpu_user": 12.0,
      "cpu_breakdown": {
        "total": 20.0,
        "user": 12.0,
        "kernel": 8.1,
        "iowait": 0.0,
        "softirq": 0.0
      },
      "memory_system_total": 5700.15,
      "memory_system_available": 3300.47,
      "memory_usage_percent": 42.1,
      "memory_percent": 42.1,
      "memory_system_used": 2399.68,
      "battery_level": 100.0,
      "network_rx_total": 6162.51,
      "network_tx_total": 2870.27,
      "network_rx": 0,
      "network_tx": 0,
      "network": 0,
      "load_1min": 23.68,
      "load_5min": 23.61,
      "load_15min": 23.4
    },
    "apps": [
      {
        "app_package": "com.hihonor.calculator",
        "cpu_usage": 5.7,
        "memory_pss": 45.95,
        "memory_java": 8.41,
        "memory_native": 5.15,
        "frame_count": 113.0,
        "jank_frames": 31.0,
        "jank_percent": 27.43,
        "gpu_p50_ms": 3.0,
        "gpu_p90_ms": 4.0,
        "gpu_p95_ms": 5.0,
        "gpu_p99_ms": 11.0,
        "power_consumption": 3900.0,
        "wakelock_count": 1,
        "top_cpu_usage": 0.0,
        "top_memory_percent": 1.5,
        "top_memory_res_kb": 89088.0,
        "app_info": {
          "package_name": "com.hihonor.calculator",
          "app_name": "com.hihonor.calculator"
        },
        "package_name": "com.hihonor.calculator"
      }
    ],
    "metadata": {
      "backend": "legacy_adb"
    }
  },
  {
    "timestamp": "2025-07-26T09:44:25.717402",
    "persisted": true,
    "system": {
      "cpu_usage": 20.0,
      "cpu_user": 12.0,
      "cpu_breakdown": {
        "total": 20.0,
        "user": 12.0,
        "kernel": 8.1,
        "iowait": 0.0,
        "softirq": 0.0
      },
      "memory_system_total": 5700.15,
      "memory_system_available": 3239.21,
      "memory_usage_percent": 43.17,
      "memory_percent": 43.17,
      "memory_system_used": 2460.94,
      "battery_level": 100.0,
      "network_rx_total": 6162.51,
      "network_tx_total": 2870.27,
      "network_rx": 0,
      "network_tx": 0,
      "network": 0,
      "load_1min": 23.68,
      "load_5min": 23.61,
      "load_15min": 23.4
    },
    "apps": [
      {
        "app_package": "com.hihonor.calculator",
        "cpu_usage": 5.7,
        "memory_pss": 40.34,
        "memory_java": 8.46,
        "memory_native": 5.07,
        "frame_count": 114.0,
        "jank_frames": 31.0,
        "jank_percent": 27.19,
        "gpu_p50_ms": 3.0,
        "gpu_p90_ms": 4.0,
        "gpu_p95_ms": 5.0,
        "gpu_p99_ms": 11.0,
        "power_consumption": 3900.0,
        "wakelock_count": 1,
        "top_cpu_usage": 0.0,
        "top_memory_percent": 1.5,
        "top_memory_res_kb": 89088.0,
        "app_info": {
          "package_name": "com.hihonor.calculator",
          "app_name": "com.hihonor.calculator"
        },
        "package_name": "com.hihonor.calculator"
      }
    ],
    "metadata": {
      "backend": "legacy_adb"
    }
  },
  {
    "timestamp": "2025-07-26T09:44:36.852169",
    "persisted": true,
    "system": {
      "cpu_usage": 20.0,
      "cpu_user": 12.0,
      "cpu_breakdown": {
        "total": 20.0,
        "user": 12.0,
        "kernel": 8.1,
        "iowait": 0.0,
        "softirq": 0.0
      },
      "memory_system_total": 5700.15,
      "memory_system_available": 3249.46,
      "memory_usage_percent": 42.99,
      "memory_percent": 42.99,
      "memory_system_used": 2450.68,
      "battery_level": 100.0,
      "network_rx_total": 6162.51,
      "network_tx_total": 2870.27,
      "network_rx": 0,
      "network_tx": 0,
      "network": 0,
      "load_1min": 23.68,
      "load_5min": 23.61,
      "load_15min": 23.4
    },
    "apps": [
      {
        "app_package": "com.hihonor.calculator",
        "cpu_usage": 5.7,
        "memory_pss": 35.25,
        "memory_java": 0.08,
        "memory_native": 0.05,
        "frame_count": 114.0,
        "jank_frames": 31.0,
        "jank_percent": 27.19,
        "gpu_p50_ms": 3.0,
        "gpu_p90_ms": 4.0,
        "gpu_p95_ms": 5.0,
        "gpu_p99_ms": 11.0,
        "power_consumption": 3900.0,
        "wakelock_count": 1,
        "top_cpu_usage": 0.0,
        "top_memory_percent": 0.9,
        "top_memory_res_kb": 55296.0,
        "app_info": {
          "package_name": "com.hihonor.calculator",
          "app_name": "com.hihonor.calculator"
        },
        "package_name": "com.hihonor.calculator"
      }
    ],
    "metadata": {
      "backend": "legacy_adb"
    }
  },
  {
    "timestamp": "2025-07-26T09:44:43.338916",
    "persisted": true,
    "system": {
      "cpu_usage": 20.0,
      "cpu_user": 12.0,
      "cpu_breakdown": {
        "total": 20.0,
        "user": 12.0,
        "kernel": 8.1,
        "iowait": 0.0,
        "softirq": 0.0
      },
      "memory_system_total": 5700.15,
      "memory_system_available": 3299.84,
      "memory_usage_percent": 42.11,
      "memory_percent": 42.11,
      "memory_system_used": 2400.3,
      "battery_level": 100.0,
      "network_rx_total": 6174.69,
      "network_tx_total": 2876.83,
      "network_rx": 1.09,
      "network_tx": 0.58,
      "network": 1.67,
      "load_1min": 23.42,
      "load_5min": 23.56,
      "load_15min": 23.38
    },
    "apps": [
      {
        "app_package": "com.hihonor.calculator",
        "cpu_usage": 5.7,
        "memory_pss": 46.08,
        "memory_java": 8.53,
        "memory_native": 5.29,
        "frame_count": 117.0,
        "jank_frames": 32.0,
        "jank_percent": 27.35,
        "gpu_p50_ms": 3.0,
        "gpu_p90_ms": 4.0,
        "gpu_p95_ms": 5.0,
        "gpu_p99_ms": 11.0,
        "power_consumption": 3900.0,
        "wakelock_count": 1,
        "top_cpu_usage": 0.0,
        "top_memory_percent": 1.5,
        "top_memory_res_kb": 90112.0,
        "app_info": {
          "package_name": "com.hihonor.calculator",
          "app_name": "com.hihonor.calculator"
        },
        "package_name": "com.hihonor.calculator"
      }
    ],
    "metadata": {
      "backend": "legacy_adb"
    }
  },
  {
    "timestamp": "2025-07-26T09:44:49.466940",
    "persisted": true,
    "system": {
      "cpu_usage": 20.0,
      "cpu_user": 12.0,
      "cpu_breakdown": {
        "total": 20.0,
        "user": 12.0,
        "kernel": 8.1,
        "iowait": 0.0,
        "softirq": 0.0
      },
      "memory_system_total": 5700.15,
      "memory_system_available": 3298.03,
      "memory_usage_percent": 42.14,
      "memory_percent": 42.14,
      "memory_system_used": 2402.12,
      "battery_level": 100.0,
      "network_rx_total": 6174.69,
      "network_tx_total": 2876.83,
      "network_rx": 0,
      "network_tx": 0,
      "network": 0,
      "load_1min": 23.42,
      "load_5min": 23.56,
      "load_15min": 23.38
    },
    "apps": [
      {
        "app_package": "com.hihonor.calculator",
        "cpu_usage": 5.7,
        "memory_pss": 45.97,
        "memory_java": 8.41,
        "memory_native": 5.29,
        "frame_count": 117.0,
        "jank_frames": 32.0,
        "jank_percent": 27.35,
        "gpu_p50_ms": 3.0,
        "gpu_p90_ms": 4.0,
        "gpu_p95_ms": 5.0,
        "gpu_p99_ms": 11.0,
        "power_consumption": 3900.0,
        "wakelock_count": 1,
        "top_cpu_usage": 0.0,
        "top_memory_percent": 1.5,
        "top_memory_res_kb": 90112.0,
        "app_info": {
          "package_name": "com.hihonor.calculator",
          "app_name": "com.hihonor.calculator"
        },
        "package_name": "com.hihonor.calculator"
      }
    ],
    "metadata": {
      "backend": "legacy_adb"
    }
  },
  {
    "timestamp": "2025-07-26T09:44:55.583275",
    "persisted": true,
    "system": {
      "cpu_usage": 20.0,
      "cpu_user": 12.0,
      "cpu_breakdown": {
        "total": 20.0,
        "user": 12.0,
        "kernel": 8.1,
        "iowait": 0.0,
        "softirq": 0.0
      },
      "memory_system_total": 5700.15,
      "memory_system_available": 3239.75,
      "memory_usage_percent": 43.16,
      "memory_percent": 43.16,
      "memory_system_used": 2460.4,
      "battery_level": 100.0,
      "network_rx_total": 6174.69,
      "network_tx_total": 2876.83,
      "network_rx": 0,
      "network_tx": 0,
      "network": 0,
      "load_1min": 23.42,
      "load_5min": 23.56,
      "load_15min": 23.38
    },
    "apps": [
      {
        "app_package": "com.hihonor.calculator",
        "cpu_usage": 5.7,
        "memory_pss": 45.43,
        "memory_java": 8.47,
        "memory_native": 5.21,
        "frame_count": 118.0,
        "jank_frames": 32.0,
        "jank_percent": 27.12,
        "gpu_p50_ms": 3.0,
        "gpu_p90_ms": 4.0,
        "gpu_p95_ms": 5.0,
        "gpu_p99_ms": 11.0,
        "power_consumption": 3900.0,
        "wakelock_count": 1,
        "top_cpu_usage": 0.0,
        "top_memory_percent": 1.5,
        "top_memory_res_kb": 89088.0,
        "app_info": {
          "package_name": "com.hihonor.calculator",
          "app_name": "com.hihonor.calculator"
        },
        "package_name": "com.hihonor.calculator"
      }
    ],
    "metadata": {
      "backend": "legacy_adb"
    }
  },
  {
    "timestamp": "2025-07-26T09:45:06.765320",
    "persisted": true,
    "system": {
      "cpu_usage": 20.0,
      "cpu_user": 12.0,
      "cpu_breakdown": {
        "total": 20.0,
        "user": 12.0,
        "kernel": 8.1,
        "iowait": 0.0,
        "softirq": 0.0
      },
      "memory_system_total": 5700.15,
      "memory_system_available": 3251.23,
      "memory_usage_percent": 42.96,
      "memory_percent": 42.96,
      "memory_system_used": 2448.92,
      "battery_level": 100.0,
      "network_rx_total": 6174.69,
      "network_tx_total": 2876.83,
      "network_rx": 0,
      "network_tx": 0,
      "network": 0,
      "load_1min": 23.42,
      "load_5min": 23.56,
      "load_15min": 23.38
    },
    "apps": [
      {
        "app_package": "com.hihonor.calculator",
        "cpu_usage": 5.7,
        "power_consumption": 3900.0,
        "wakelock_count": 1,
        "top_cpu_usage": 0.0,
        "top_memory_percent": 0.9,
        "top_memory_res_kb": 55296.0,
        "app_info": {
          "package_name": "com.hihonor.calculator",
          "app_name": "com.hihonor.calculator"
        },
        "package_name": "com.hihonor.calculator"
      }
    ],
    "metadata": {
      "backend": "legacy_adb"
    }
  },
  {
    "timestamp": "2025-07-26T09:45:13.162151",
    "persisted": true,
    "system": {
      "cpu_usage": 20.0,
      "cpu_user": 12.0,
      "cpu_breakdown": {
        "total": 20.0,
        "user": 12.0,
        "kernel": 8.1,
        "iowait": 0.0,
        "softirq": 0.0
      },
      "memory_system_total": 5700.15,
      "memory_system_available": 3294.8,
      "memory_usage_percent": 42.2,
      "memory_percent": 42.2,
      "memory_system_used": 2405.34,
      "battery_level": 100.0,
      "network_rx_total": 6174.69,
      "network_tx_total": 2876.83,
      "network_rx": 0,
      "network_tx": 0,
      "network": 0,
      "load_1min": 23.42,
      "load_5min": 23.56,
      "load_15min": 23.38
    },
    "apps": [
      {
        "app_package": "com.hihonor.calculator",
        "cpu_usage": 5.7,
        "memory_pss": 46.12,
        "memory_java": 8.61,
        "memory_native": 5.12,
        "frame_count": 121.0,
        "jank_frames": 33.0,
        "jank_percent": 27.27,
        "gpu_p50_ms": 3.0,
        "gpu_p90_ms": 4.0,
        "gpu_p95_ms": 5.0,
        "gpu_p99_ms": 11.0,
        "power_consumption": 3900.0,
        "wakelock_count": 1,
        "top_cpu_usage": 0.0,
        "top_memory_percent": 1.5,
        "top_memory_res_kb": 90112.0,
        "app_info": {
          "package_name": "com.hihonor.calculator",
          "app_name": "com.hihonor.calculator"
        },
        "package_name": "com.hihonor.calculator"
      }
    ],
    "metadata": {
      "backend": "legacy_adb"
    }
  },
  {
    "timestamp": "2025-07-26T09:45:19.521368",
    "persisted": true,
    "system": {
      "cpu_usage": 20.0,
      "cpu_user": 12.0,
      "cpu_breakdown": {
        "total": 20.0,
        "user": 12.0,
        "kernel": 8.1,
        "iowait": 0.0,
        "softirq": 0.0
      },
      "memory_system_total": 5700.15,
      "memory_system_available": 3307.0,
      "memory_usage_percent": 41.98,
      "memory_percent": 41.98,
      "memory_system_used": 2393.15,
      "battery_level": 100.0,
      "network_rx_total": 6188.66,
      "network_tx_total": 2883.37,
      "network_rx": 2.16,
      "network_tx": 1.01,
      "network": 3.17,
      "load_1min": 23.65,
      "load_5min": 23.6,
      "load_15min": 23.41
    },
    "apps": [
      {
        "app_package": "com.hihonor.calculator",
        "cpu_usage": 5.7,
        "memory_pss": 45.92,
        "memory_java": 8.41,
        "memory_native": 5.12,
        "frame_count": 121.0,
        "jank_frames": 33.0,
        "jank_percent": 27.27,
        "gpu_p50_ms": 3.0,
        "gpu_p90_ms": 4.0,
        "gpu_p95_ms": 5.0,
        "gpu_p99_ms": 11.0,
        "power_consumption": 3900.0,
        "wakelock_count": 1,
        "top_cpu_usage": 0.0,
        "top_memory_percent": 1.5,
        "top_memory_res_kb": 90112.0,
        "app_info": {
          "package_name": "com.hihonor.calculator",
          "app_name": "com.hihonor.calculator"
        },
        "package_name": "com.hihonor.calculator"
      }
    ],
    "metadata": {
      "backend": "legacy_adb"
    }
  },
  {
    "timestamp": "2025-07-26T09:45:25.769967",
    "persisted": true,
    "system": {
      "cpu_usage": 20.0,
      "cpu_user": 12.0,
      "cpu_breakdown": {
        "total": 20.0,
        "user": 12.0,
        "kernel": 8.1,
        "iowait": 0.0,
        "softirq": 0.0
      },
      "memory_system_total": 5700.15,
      "memory_system_available": 3237.6,
      "memory_usage_percent": 43.2,
      "memory_percent": 43.2,
      "memory_system_used": 2462.55,
      "battery_level": 100.0,
      "network_rx_total": 6188.66,
      "network_tx_total": 2883.37,
      "network_rx": 0,
      "network_tx": 0,
      "network": 0,
      "load_1min": 23.65,
      "load_5min": 23.6,
      "load_15min": 23.41
    },
    "apps": [
      {
        "app_package": "com.hihonor.calculator",
        "cpu_usage": 5.7,
        "memory_pss": 45.34,
        "memory_java": 8.46,
        "memory_native": 5.06,
        "frame_count": 122.0,
        "jank_frames": 33.0,
        "jank_percent": 27.05,
        "gpu_p50_ms": 3.0,
        "gpu_p90_ms": 4.0,
        "gpu_p95_ms": 6.0,
        "gpu_p99_ms": 11.0,
        "power_consumption": 3900.0,
        "wakelock_count": 1,
        "top_cpu_usage": 0.0,
        "top_memory_percent": 1.5,
        "top_memory_res_kb": 89088.0,
        "app_info": {
          "package_name": "com.hihonor.calculator",
          "app_name": "com.hihonor.calculator"
        },
        "package_name": "com.hihonor.calculator"
      }
    ],
    "metadata": {
      "backend": "legacy_adb"
    }
  },
  {
    "timestamp": "2025-07-26T09:45:36.918269",
    "persisted": true,
    "system": {
      "cpu_usage": 20.0,
      "cpu_user": 12.0,
      "cpu_breakdown": {
        "total": 20.0,
        "user": 12.0,
        "kernel": 8.1,
        "iowait": 0.0,
        "softirq": 0.0
      },
      "memory_system_total": 5700.15,
      "memory_system_available": 3246.88,
      "memory_usage_percent": 43.04,
      "memory_percent": 43.04,
      "memory_system_used": 2453.27,
      "battery_level": 100.0,
      "network_rx_total": 6188.66,
      "network_tx_total": 2883.37,
      "network_rx": 0,
      "network_tx": 0,
      "network": 0,
      "load_1min": 23.65,
      "load_5min": 23.6,
      "load_15min": 23.41
    },
    "apps": [
      {
        "app_package": "com.hihonor.calculator",
        "cpu_usage": 5.7,
        "power_consumption": 3900.0,
        "wakelock_count": 1,
        "top_cpu_usage": 0.0,
        "top_memory_percent": 0.9,
        "top_memory_res_kb": 55296.0,
        "app_info": {
          "package_name": "com.hihonor.calculator",
          "app_name": "com.hihonor.calculator"
        },
        "package_name": "com.hihonor.calculator"
      }
    ],
    "metadata": {
      "backend": "legacy_adb"
    }
  },
  {
    "timestamp": "2025-07-26T09:45:43.430622",
    "persisted": true,
    "system": {
      "cpu_usage": 20.0,
      "cpu_user": 12.0,
      "cpu_breakdown": {
        "total": 20.0,
        "user": 12.0,
        "kernel": 8.1,
        "iowait": 0.0,
        "softirq": 0.0
      },
      "memory_system_total": 5700.15,
      "memory_system_available": 3241.42,
      "memory_usage_percent": 43.13,
      "memory_percent": 43.13,
      "memory_system_used": 2458.73,
      "battery_level": 100.0,
      "network_rx_total": 6188.66,
      "network_tx_total": 2883.37,
      "network_rx": 0,
      "network_tx": 0,
      "network": 0,
      "load_1min": 23.65,
      "load_5min": 23.6,
      "load_15min": 23.41
    },
    "apps": [
      {
        "app_package": "com.hihonor.calculator",
        "cpu_usage": 5.7,
        "power_consumption": 3900.0,
        "wakelock_count": 1,
        "top_cpu_usage": 0.0,
        "top_memory_percent": 0.9,
        "top_memory_res_kb": 56320.0,
        "app_info": {
          "package_name": "com.hihonor.calculator",
          "app_name": "com.hihonor.calculator"
        },
        "package_name": "com.hihonor.calculator"
      }
    ],
    "metadata": {
      "backend": "legacy_adb"
    }
  }
]